flask_mvc_core/__init__.py
flask_mvc_core/__version__.py
flask_mvc_core/flask_mvc_blueprint.py
flask_mvc_core/flask_mvc_core.py
flask_mvc_core/request.py
flask_mvc_core/response.py
flask_mvc_core-0.1.2.dist-info/LICENSE
flask_mvc_core-0.1.2.dist-info/METADATA
flask_mvc_core-0.1.2.dist-info/WHEEL
flask_mvc_core-0.1.2.dist-info/top_level.txt
flask_mvc_core-0.1.2.dist-info/RECORD
