Metadata-Version: 2.1
Name: flask-mvc-core
Version: 0.1.2
Summary: Wrapper personalizado para Flask com estrutura MVC
Home-page: https://github.com/celiovmjr/flask-mvc-core
Author: Célio Junior
Author-email: profissional.celiojunior@outlook.com
Classifier: Programming Language :: Python :: 3
Classifier: License :: OSI Approved :: MIT License
Classifier: Operating System :: OS Independent
Requires-Python: >=3.10
License-File: LICENSE
Requires-Dist: Flask>=3.0.0
Requires-Dist: waitress
